synonym_custom/__init__.py
synonym_custom/synonym_custom.py
synonym_custom-0.1.3.dist-info/METADATA
synonym_custom-0.1.3.dist-info/WHEEL
synonym_custom-0.1.3.dist-info/top_level.txt
synonym_custom-0.1.3.dist-info/RECORD
