Metadata-Version: 2.1
Name: synonym-custom
Version: 0.1.3
Author: Sandeep Chataut
Requires-Python: >=3.8
Requires-Dist: openai (==0.27.7)
Requires-Dist: requests (==2.28.1)
Requires-Dist: spacy (==3.5.3)
Requires-Dist: spacy-wordnet (==0.1.0)
Requires-Dist: python-dotenv (==1.0.0)
Requires-Dist: nltk (==3.5)
Requires-Dist: transformers (==4.29.2)
Requires-Dist: beautifulsoup4 (==4.11.1)
